netshow_core-1.1.3-py2.7-nspkg.pth
netshow_core-1.1.3.dist-info/METADATA
netshow_core-1.1.3.dist-info/RECORD
netshow_core-1.1.3.dist-info/metadata.json
netshow_core-1.1.3.dist-info/WHEEL
netshow_core-1.1.3.dist-info/DESCRIPTION.rst
netshow_core-1.1.3.dist-info/namespace_packages.txt
netshow_core-1.1.3.dist-info/top_level.txt
netshow/_version.py
netshow/netshow.py
netshow_core-1.1.3.data/scripts/netshow
netshow_core-1.1.3.data/data/share/man/man1/netshow.1
netshow_core-1.1.3.data/data/share/bash-completion/completions/netshow
