Metadata-Version: 2.0
Name: netshow-core
Version: 1.1.3
Summary: Linux Network Troubleshooting Tool
Home-page: http://github.com/CumulusNetworks/netshow-core
Author: Cumulus Networks
Author-email: ce-ceng@cumulusnetworks.com
License: GPLv2
Platform: UNKNOWN
Classifier: Development Status :: 4 - Beta
Classifier: Topic :: System :: Networking
Classifier: Intended Audience :: System Administrators
Classifier: Operating System :: POSIX :: Linux
Requires-Dist: setuptools
Requires-Dist: netshow-core-lib
